flask_filerev.py
setup.py
Flask_FileRev.egg-info/PKG-INFO
Flask_FileRev.egg-info/SOURCES.txt
Flask_FileRev.egg-info/dependency_links.txt
Flask_FileRev.egg-info/requires.txt
Flask_FileRev.egg-info/top_level.txt
flask_filerev.egg-info/PKG-INFO
flask_filerev.egg-info/SOURCES.txt
flask_filerev.egg-info/dependency_links.txt
flask_filerev.egg-info/requires.txt
flask_filerev.egg-info/top_level.txt