Metadata-Version: 1.0
Name: Flask-FileRev
Version: 0.1.0
Summary: Flask-FileRev
Home-page: https://github.com/raicheff/flask-filerev
Author: Boris Raicheff
Author-email: b@raicheff.com
License: UNKNOWN
Platform: UNKNOWN
